{
 "kind": "FileDocument",
 "id": "README.md",
 "isDeleted": false,
 "rev": "",
 "description": "",
 "name": "README.md",
 "acl": {
  "kind": "Acl",
  "owner": "",
  "aces": []
 },
 "createdDate": {
  "kind": "Date",
  "value": ""
 },
 "lastModifiedDate": {
  "kind": "Date",
  "value": ""
 },
 "urls": [],
 "tags": [],
 "meta": [],
 "url": {
  "kind": "Url",
  "uri": ""
 },
 "version": "",
 "isPublic": false,
 "projectId": "",
 "folderId": "",
 "dataUri": "lfs/5b/5c/750163ec05b26b003e69990784ef937ab71928924312d5cf357e51e51991",
 "metadata": {
  "kind": "FileMetadata",
  "contentType": "",
  "cacheControl": "",
  "contentEncoding": "",
  "contentLanguage": "",
  "md5Hash": ""
 },
 "size": 937
}