{
 "kind": "ComputedTableSchema",
 "id": "08b7fadf10fe97438f5deb8ec56dcf1c31e92e4c5655d10e7c4024579cb95f34",
 "isDeleted": false,
 "rev": "",
 "description": "",
 "name": "b45caca0-1a9f-11f0-9797-a957102c1d69",
 "acl": {
  "kind": "Acl",
  "owner": "",
  "aces": []
 },
 "createdDate": {
  "kind": "Date",
  "value": ""
 },
 "lastModifiedDate": {
  "kind": "Date",
  "value": ""
 },
 "urls": [],
 "tags": [],
 "meta": [
  {
   "kind": "Pair",
   "key": "SHA256",
   "value": "08b7fadf10fe97438f5deb8ec56dcf1c31e92e4c5655d10e7c4024579cb95f34"
  }
 ],
 "url": {
  "kind": "Url",
  "uri": ""
 },
 "version": "",
 "isPublic": false,
 "projectId": "",
 "folderId": "",
 "nRows": 188000,
 "columns": [
  {
   "kind": "ColumnSchema",
   "id": "ddf673eb-1b72-453a-b9d4-5030b7a3088f",
   "name": "ds1.scaled_value",
   "type": "double",
   "nRows": 0,
   "size": -1,
   "metaData": {
    "kind": "ColumnSchemaMetaData",
    "sort": [],
    "ascending": true,
    "quartiles": [],
    "properties": []
   }
  },
  {
   "kind": "ColumnSchema",
   "id": "18764caa-1f94-4742-89a7-511b473c5959",
   "name": ".ci",
   "type": "int32",
   "nRows": 0,
   "size": -1,
   "metaData": {
    "kind": "ColumnSchemaMetaData",
    "sort": [],
    "ascending": true,
    "quartiles": [],
    "properties": []
   }
  },
  {
   "kind": "ColumnSchema",
   "id": "beb2b82a-eda0-4f8a-a270-c512f64cb26a",
   "name": ".ri",
   "type": "int32",
   "nRows": 0,
   "size": -1,
   "metaData": {
    "kind": "ColumnSchemaMetaData",
    "sort": [],
    "ascending": true,
    "quartiles": [],
    "properties": []
   }
  }
 ],
 "dataDirectory": "data/08/b7/08b7fadf10fe97438f5deb8ec56dcf1c31e92e4c5655d10e7c4024579cb95f34",
 "relation": {
  "kind": "Relation",
  "id": "aa594d9c-804c-4f8c-8018-6c0ae1aa08eb"
 },
 "size": 1644112,
 "query": {
  "kind": "CubeQuery",
  "relation": {
   "kind": "CompositeRelation",
   "id": "d5313a42-a44b-41df-b7f1-55f4320ea235",
   "joinOperators": [
    {
     "kind": "JoinOperator",
     "joinType": "leftOuter",
     "leftPair": {
      "kind": "ColumnPair",
      "lColumns": [
       "channel_id"
      ],
      "rColumns": [
       "channel_id"
      ]
     },
     "rightRelation": {
      "kind": "SimpleRelation",
      "id": "61307a38e13569f00693c04608a76ea47e74dd03a0390fd0daab9686a4580db1",
      "index": 1
     }
    }
   ],
   "mainRelation": {
    "kind": "SimpleRelation",
    "id": "ab4a9083a99a61dc2ed7b76bdd2cef3958df5ab7e9607afae623f1efe440a3e5",
    "index": 0
   }
  },
  "colColumns": [
   {
    "kind": "Factor",
    "name": "channel_name",
    "type": "string"
   },
   {
    "kind": "Factor",
    "name": "channel_description",
    "type": "string"
   }
  ],
  "rowColumns": [
   {
    "kind": "Factor",
    "name": "event_id",
    "type": "double"
   }
  ],
  "axisQueries": [
   {
    "kind": "CubeAxisQuery",
    "pointSize": 4,
    "chartType": "point",
    "yAxis": {
     "kind": "Factor",
     "name": "value",
     "type": "double"
    },
    "yAxisSettings": {
     "kind": "AxisSettings",
     "meta": []
    },
    "xAxis": {
     "kind": "Factor",
     "name": "",
     "type": "string"
    },
    "xAxisSettings": {
     "kind": "AxisSettings",
     "meta": []
    },
    "errors": [],
    "labels": [],
    "colors": [],
    "preprocessors": []
   }
  ],
  "filters": {
   "kind": "Filters",
   "removeNaN": true,
   "namedFilters": []
  },
  "operatorSettings": {
   "kind": "OperatorSettings",
   "namespace": "ds1",
   "operatorRef": {
    "kind": "OperatorRef",
    "name": "Scale (Z-Score)",
    "version": "58e970f7009834184693775f67167be0cd6e39bc",
    "operatorId": "1",
    "operatorKind": "ROperator",
    "propertyValues": [
     {
      "kind": "PropertyValue",
      "name": "scale",
      "value": "true"
     },
     {
      "kind": "PropertyValue",
      "name": "center",
      "value": "true"
     }
    ],
    "url": {
     "kind": "Url",
     "uri": "https://github.com/tercen/scale_operator"
    },
    "operatorSpec": {
     "kind": "OperatorSpec",
     "ontologyUri": "https://tercen.com/_ontology/tercen",
     "ontologyVersion": "0.0.1",
     "inputSpecs": [
      {
       "kind": "CrosstabSpec",
       "metaFactors": [
        {
         "kind": "MetaFactor",
         "name": "Channel",
         "type": "",
         "description": "The channel identifiers",
         "ontologyMapping": "variable",
         "crosstabMapping": "column",
         "cardinality": "1..n",
         "factors": [
          {
           "kind": "Factor",
           "name": "channel_name",
           "type": "string"
          },
          {
           "kind": "Factor",
           "name": "channel_description",
           "type": "string"
          }
         ]
        },
        {
         "kind": "MetaFactor",
         "name": "events",
         "type": "",
         "description": "the observations",
         "ontologyMapping": "observation",
         "crosstabMapping": "row",
         "cardinality": "1..n",
         "factors": [
          {
           "kind": "Factor",
           "name": "event_id",
           "type": "double"
          }
         ]
        }
       ],
       "axis": [
        {
         "kind": "AxisSpec",
         "metaFactors": [
          {
           "kind": "MetaFactor",
           "name": "data",
           "type": "numeric",
           "description": "the measurements",
           "ontologyMapping": "measurement",
           "crosstabMapping": "y",
           "cardinality": "1",
           "factors": [
            {
             "kind": "Factor",
             "name": "value",
             "type": "double"
            }
           ]
          }
         ]
        }
       ]
      }
     ],
     "outputSpecs": []
    }
   },
   "environment": [],
   "operatorModel": {
    "kind": "OperatorModel"
   }
  },
  "qtHash": "",
  "columnHash": "",
  "rowHash": ""
 }
}